cobinhood_api/cobinhood.py
cobinhood_api/__init__.py
cobinhood_api-1.0.dist-info/DESCRIPTION.rst
cobinhood_api-1.0.dist-info/METADATA
cobinhood_api-1.0.dist-info/metadata.json
cobinhood_api-1.0.dist-info/RECORD
cobinhood_api-1.0.dist-info/top_level.txt
cobinhood_api-1.0.dist-info/WHEEL
