Metadata-Version: 2.0
Name: cobinhood-api
Version: 1.0
Summary: API wrapper for Cobinhood exchange written in Python
Home-page: https://github.com/thomasbeukema/cobinhood_api
Author: Thomas Beukema
Author-email: thomas@thomasbeukema.me
License: MIT
Download-URL: https://github.com/thomasbeukema/cobinhood_api/archive/1.0.tar.gz
Keywords: cobinhood,api,crypto,exchange
Platform: UNKNOWN
Classifier: Development Status :: 4 - Beta
Classifier: Programming Language :: Python :: 3
Classifier: License :: OSI Approved :: MIT License
Classifier: Intended Audience :: Developers
Requires-Python: >=3
